[{"iGols":1,"sNmJogador":"GASTÓN RODRIGUEZ MAESO","sApelido":"GASTÓN","sFoto":"http://egol.fcf.com.br/sesp/Images/80150249942_43_gastan.png","sClube":"AVAÍ","sLogo":"http://egol.fcf.com.br/SESP/ClubeLigas/avai.png"},{"iGols":1,"sNmJogador":"JOAO PAULO FERREIRA LOURENCO","sApelido":"LOURENÇO","sFoto":"http://egol.fcf.com.br/sesp/Images/02169466622_20_lourenco.png","sClube":"AVAÍ","sLogo":"http://egol.fcf.com.br/SESP/ClubeLigas/avai.png"},{"iGols":1,"sNmJogador":"VINICIUS RAYAN PEREIRA DOS SANTOS","sApelido":"RAYAN","sFoto":"http://egol.fcf.com.br/sesp/Images/00057528179_11_Foto.JPG","sClube":"TUBARÃO","sLogo":"http://egol.fcf.com.br/SESP/ClubeLigas/TUBARAO.png"},{"iGols":1,"sNmJogador":"NICHOLAS DE SOUZA LENCZCZAK","sApelido":"NICHOLAS","sFoto":"http://egol.fcf.com.br/sesp/Images/03329566019_66_Nicholas.jpg","sClube":"FIGUEIRENSE","sLogo":"http://egol.fcf.com.br/SESP/ClubeLigas/FIGUEIRENSE.png"},{"iGols":1,"sNmJogador":"GILEARD NASCIMENTO BORGES","sApelido":"GILEARD","sFoto":"http://egol.fcf.com.br/sesp/Images/60863389309_78_Foto.JPG","sClube":"TUBARÃO","sLogo":"http://egol.fcf.com.br/SESP/ClubeLigas/TUBARAO.png"},{"iGols":1,"sNmJogador":"VINICIUS GUEDES","sApelido":"GUEDES","sFoto":"http://egol.fcf.com.br/sesp/Images/02105689094_94_Guedes.jpg","sClube":"CHAPECOENSE","sLogo":"http://egol.fcf.com.br/SESP/ClubeLigas/Chapecoense.png"},{"iGols":1,"sNmJogador":"JOAO CARLOS BARROS LOPES","sApelido":"JOAO","sFoto":"http://egol.fcf.com.br/sesp/Images/10451043960_33_Joao.JPG","sClube":"CRICIÚMA","sLogo":"http://egol.fcf.com.br/SESP/ClubeLigas/CRICIUMA.png"},{"iGols":1,"sNmJogador":"JANDIR BRENO SOUZA SILVA","sApelido":"JANDIR","sFoto":"http://egol.fcf.com.br/sesp/Images/09963560610_91_Jaja2.jpg","sClube":"CRICIÚMA","sLogo":"http://egol.fcf.com.br/SESP/ClubeLigas/CRICIUMA.png"},{"iGols":1,"sNmJogador":"ADRIANO SOARES FILGUEIRA","sApelido":"ADRIANO","sFoto":"http://egol.fcf.com.br/sesp/Images/00519376110_33_ADRIANO.jpg","sClube":"JOINVILLE","sLogo":"http://egol.fcf.com.br/SESP/ClubeLigas/Joinville.png"},{"iGols":1,"sNmJogador":"VITOR CORREIA DA SILVA","sApelido":"VITOR","sFoto":"http://egol.fcf.com.br/sesp/Images/45781248862_8_FEIJaO.jpg","sClube":"FIGUEIRENSE","sLogo":"http://egol.fcf.com.br/SESP/ClubeLigas/FIGUEIRENSE.png"},{"iGols":1,"sNmJogador":"GUSTAVO BRANDENBURG","sApelido":"GUSTAVO","sFoto":"http://egol.fcf.com.br/sesp/Images/09120380984_28_3x4.jpg","sClube":"JOINVILLE","sLogo":"http://egol.fcf.com.br/SESP/ClubeLigas/Joinville.png"},{"iGols":1,"sNmJogador":"RODRIGO FERREIRA DA SILVA","sApelido":"","sFoto":"http://egol.fcf.com.br/sesp/Images/44266070861_21_wel.jpeg","sClube":"MARCÍLIO DIAS","sLogo":"http://egol.fcf.com.br/SESP/ClubeLigas/marciliodias.png"},{"iGols":1,"sNmJogador":"JOSE MARCOS ALVES LUIS","sApelido":"ZÉ MARCOS","sFoto":"http://egol.fcf.com.br/sesp/Images/10183190939_57_ZeMarcos.JPG","sClube":"AVAÍ","sLogo":"http://egol.fcf.com.br/SESP/ClubeLigas/avai.png"},{"iGols":1,"sNmJogador":"LEONARDO MATTOS DA SILVA","sApelido":"DA SILVA","sFoto":"http://egol.fcf.com.br/sesp/Images/03029021041_63_dasilva.png","sClube":"AVAÍ","sLogo":"http://egol.fcf.com.br/SESP/ClubeLigas/avai.png"},{"iGols":1,"sNmJogador":"DANIEL LOPES DE ANDRADE","sApelido":"DANDAN","sFoto":"http://egol.fcf.com.br/sesp/Images/14102583785_99_Dandan.jpg","sClube":"BRUSQUE","sLogo":"http://egol.fcf.com.br/SESP/ClubeLigas/Brusque.png"},{"iGols":1,"sNmJogador":"LUCAS ITAMIR DE SA","sApelido":"LUCAS DE SÁ","sFoto":"http://egol.fcf.com.br/sesp/Images/09373388932_16_foto3x4.jpg","sClube":"JOINVILLE","sLogo":"http://egol.fcf.com.br/SESP/ClubeLigas/Joinville.png"},{"iGols":1,"sNmJogador":"PAULO ROBERTO MOCCELIN","sApelido":"PAULO","sFoto":"http://egol.fcf.com.br/sesp/Images/03031938089_55_Paulo.jpg","sClube":"CHAPECOENSE","sLogo":"http://egol.fcf.com.br/SESP/ClubeLigas/Chapecoense.png"},{"iGols":1,"sNmJogador":"ANDERSON RODRIGUES DA LUZ","sApelido":"ANDERSON LIGEIRO","sFoto":"http://egol.fcf.com.br/sesp/Images/42862699810_18_LIG.jpg","sClube":"MARCÍLIO DIAS","sLogo":"http://egol.fcf.com.br/SESP/ClubeLigas/marciliodias.png"},{"iGols":1,"sNmJogador":"AYLON DARWIN TAVELLA","sApelido":"AYLON","sFoto":"http://egol.fcf.com.br/sesp/Images/02003042083_98_29.png","sClube":"CHAPECOENSE","sLogo":"http://egol.fcf.com.br/SESP/ClubeLigas/Chapecoense.png"},{"iGols":1,"sNmJogador":"MIKAEL GUTERRES MICHEL","sApelido":"MIKAEL","sFoto":"http://egol.fcf.com.br/sesp/Images/82036519091_17_MIKAEL.jpeg","sClube":"JUVENTUS","sLogo":"http://egol.fcf.com.br/SESP/ClubeLigas/JUVENTUS.png"},{"iGols":1,"sNmJogador":"GUILHERME SEEFELDT KROLOW","sApelido":"FOGUINHO","sFoto":"http://egol.fcf.com.br/sesp/Images/02412125023_43_Foguinho.JPG","sClube":"CRICIÚMA","sLogo":"http://egol.fcf.com.br/SESP/ClubeLigas/CRICIUMA.png"},{"iGols":1,"sNmJogador":"WANDERSON FERREIRA DE OLIVEIRA","sApelido":"VALDIVIA","sFoto":"http://egol.fcf.com.br/sesp/Images/03247403108_73_Valdivia.png","sClube":"AVAÍ","sLogo":"http://egol.fcf.com.br/SESP/ClubeLigas/avai.png"},{"iGols":1,"sNmJogador":"MATHEUS ANTUNES RIBEIRO","sApelido":"MATHEUS","sFoto":"http://egol.fcf.com.br/sesp/Images/02738491073_92_matheus.jpg","sClube":"CHAPECOENSE","sLogo":"http://egol.fcf.com.br/SESP/ClubeLigas/Chapecoense.png"},{"iGols":1,"sNmJogador":"DIOGO LIMA CALIXTO","sApelido":"DIOGO","sFoto":"http://egol.fcf.com.br/sesp/Images/40535866828_65_CALIXTO.jpg","sClube":"CONCÓRDIA","sLogo":"http://egol.fcf.com.br/SESP/ClubeLigas/CONCORDIA.png"},{"iGols":1,"sNmJogador":"DENNER PAULINO BARBOSA","sApelido":"DENNER","sFoto":"http://egol.fcf.com.br/sesp/Images/39746146807_31_denner.jpeg","sClube":"JUVENTUS","sLogo":"http://egol.fcf.com.br/SESP/ClubeLigas/JUVENTUS.png"},{"iGols":1,"sNmJogador":"LUCAS RODRIGUES RAMOS DA SILVA","sApelido":"LUCAS","sFoto":"http://egol.fcf.com.br/sesp/Images/40569940800_71_ramos.jpg","sClube":"CONCÓRDIA","sLogo":"http://egol.fcf.com.br/SESP/ClubeLigas/CONCORDIA.png"},{"iGols":1,"sNmJogador":"RODRIGO DA ROSA MILANEZ","sApelido":"RODRIGO","sFoto":"http://egol.fcf.com.br/sesp/Images/06754002956_34_Rodrigo.JPG","sClube":"CRICIÚMA","sLogo":"http://egol.fcf.com.br/SESP/ClubeLigas/CRICIUMA.png"},{"iGols":1,"sNmJogador":"IANSON ACOSTA SOARES","sApelido":"IANSON","sFoto":"http://egol.fcf.com.br/sesp/Images/02949153038_17_Ianson.png","sClube":"BRUSQUE","sLogo":"http://egol.fcf.com.br/SESP/ClubeLigas/Brusque.png"},{"iGols":1,"sNmJogador":"WALLACE SANTOS ACIOLI","sApelido":"WALLACE ACIOLI","sFoto":"http://egol.fcf.com.br/sesp/Images/09941776407_4_311161.jpg","sClube":"MARCÍLIO DIAS","sLogo":"http://egol.fcf.com.br/SESP/ClubeLigas/marciliodias.png"},{"iGols":1,"sNmJogador":"ANDREW LUCAS BALBINO DRUMMOND","sApelido":"ANDREW","sFoto":"http://egol.fcf.com.br/sisgol/arbitros/semfoto.png","sClube":"CRICIÚMA","sLogo":"http://egol.fcf.com.br/SESP/ClubeLigas/CRICIUMA.png"},{"iGols":1,"sNmJogador":"ROBERT ALEXANDRE FISCHER","sApelido":"ROBERT","sFoto":"http://egol.fcf.com.br/sesp/Images/08261968960_97_foto3x4.jpg","sClube":"JOINVILLE","sLogo":"http://egol.fcf.com.br/SESP/ClubeLigas/Joinville.png"},{"iGols":1,"sNmJogador":"MATHEUS TRINDADE GONÇALVES","sApelido":"MATHEUS TRINDADE","sFoto":"http://egol.fcf.com.br/sesp/Images/14528440709_3_foto3x4.jpg","sClube":"JOINVILLE","sLogo":"http://egol.fcf.com.br/SESP/ClubeLigas/Joinville.png"},{"iGols":1,"sNmJogador":"DAVI XAVIER LOPES DOS SANTOS","sApelido":"DAVI LOPES","sFoto":"http://egol.fcf.com.br/sesp/Images/36476591851_44_Foto.JPG","sClube":"TUBARÃO","sLogo":"http://egol.fcf.com.br/SESP/ClubeLigas/TUBARAO.png"},{"iGols":1,"sNmJogador":"AIRTON TIRABASSI","sApelido":"AIRTON","sFoto":"http://egol.fcf.com.br/sesp/Images/39839712888_57_Airton.png","sClube":"AVAÍ","sLogo":"http://egol.fcf.com.br/SESP/ClubeLigas/avai.png"},{"iGols":1,"sNmJogador":"CHARLES LUIS REITER","sApelido":"CHARLES","sFoto":"http://egol.fcf.com.br/sesp/Images/05318387900_92_3x4.jpg","sClube":"JOINVILLE","sLogo":"http://egol.fcf.com.br/SESP/ClubeLigas/Joinville.png"},{"iGols":1,"sNmJogador":"PEDRO HENRIQUE DE CASTRO SILVA","sApelido":"PEDRO CASTRO","sFoto":"http://egol.fcf.com.br/sesp/Images/13864209722_42_pcastro.png","sClube":"AVAÍ","sLogo":"http://egol.fcf.com.br/SESP/ClubeLigas/avai.png"},{"iGols":1,"sNmJogador":"TITO FERNANDO DA SILVA PINTO","sApelido":"TITO","sFoto":"http://egol.fcf.com.br/sesp/Images/02883304122_7_TITO.jpg","sClube":"CONCÓRDIA","sLogo":"http://egol.fcf.com.br/SESP/ClubeLigas/CONCORDIA.png"},{"iGols":1,"sNmJogador":"TULIO RENAN SOUZA XAVIER","sApelido":"TULIO","sFoto":"http://egol.fcf.com.br/sesp/Images/04051545504_28_foto.jpg","sClube":"JUVENTUS","sLogo":"http://egol.fcf.com.br/SESP/ClubeLigas/JUVENTUS.png"},{"iGols":1,"sNmJogador":"DIEGO FELIPE COUTINHO","sApelido":"DIEGO","sFoto":"http://egol.fcf.com.br/sesp/Images/13453113705_22_DIEGO.jpg","sClube":"CONCÓRDIA","sLogo":"http://egol.fcf.com.br/SESP/ClubeLigas/CONCORDIA.png"},{"iGols":1,"sNmJogador":"RAFAEL BERGER","sApelido":"ALEMÃO","sFoto":"http://egol.fcf.com.br/sesp/Images/11563324784_88_Rafael.jpg","sClube":"FIGUEIRENSE","sLogo":"http://egol.fcf.com.br/SESP/ClubeLigas/FIGUEIRENSE.png"},{"iGols":1,"sNmJogador":"EDSON RAMOS DA SILVA","sApelido":"EDSON","sFoto":"http://egol.fcf.com.br/sesp/Images/06389033435_75_3x4.jpg","sClube":"JOINVILLE","sLogo":"http://egol.fcf.com.br/SESP/ClubeLigas/Joinville.png"},{"iGols":1,"sNmJogador":"MARCO ANTONIO DE MATTOS FILHO","sApelido":"MARCO","sFoto":"http://egol.fcf.com.br/sesp/Images/00357997069_8_foto15.jpeg","sClube":"FIGUEIRENSE","sLogo":"http://egol.fcf.com.br/SESP/ClubeLigas/FIGUEIRENSE.png"},{"iGols":2,"sNmJogador":"JOSE VITOR DOS SANTOS SILVA","sApelido":"ZÉ VITOR","sFoto":"http://egol.fcf.com.br/sesp/Images/07614054539_43_Ze.JPG","sClube":"TUBARÃO","sLogo":"http://egol.fcf.com.br/SESP/ClubeLigas/TUBARAO.png"},{"iGols":2,"sNmJogador":"VINICIUS XAVIER DA PURIFICAÇÃO MOUTINHO","sApelido":"VINIICUS","sFoto":"http://egol.fcf.com.br/sesp/Images/14302644621_35_vini.jpg","sClube":"CHAPECOENSE","sLogo":"http://egol.fcf.com.br/SESP/ClubeLigas/Chapecoense.png"},{"iGols":2,"sNmJogador":"FERNANDO JOSE MARQUES MACIEL","sApelido":"FERNANDINHO","sFoto":"http://egol.fcf.com.br/sesp/Images/60518860361_24_3x4.jpg","sClube":"JOINVILLE","sLogo":"http://egol.fcf.com.br/SESP/ClubeLigas/Joinville.png"},{"iGols":2,"sNmJogador":"GEOVANE SANTANA SOUZA","sApelido":"GEOVANE","sFoto":"http://egol.fcf.com.br/sesp/Images/06899348586_7_foto.jpg","sClube":"JUVENTUS","sLogo":"http://egol.fcf.com.br/SESP/ClubeLigas/JUVENTUS.png"},{"iGols":2,"sNmJogador":"DIEGO GONÇALVES","sApelido":"DIEGO","sFoto":"http://egol.fcf.com.br/sesp/Images/43621845895_80_DIEGO.jpg","sClube":"FIGUEIRENSE","sLogo":"http://egol.fcf.com.br/SESP/ClubeLigas/FIGUEIRENSE.png"},{"iGols":2,"sNmJogador":"WILLIAN DOS SANTOS MEDINA","sApelido":"WILLIAN","sFoto":"http://egol.fcf.com.br/sesp/Images/10971160694_32_foto.jpg","sClube":"MARCÍLIO DIAS","sLogo":"http://egol.fcf.com.br/SESP/ClubeLigas/marciliodias.png"},{"iGols":2,"sNmJogador":"PEDRO LUCAS SCHWAIZER","sApelido":"PEDRO LUCAS","sFoto":"http://egol.fcf.com.br/sesp/Images/01008262021_81_PEDRO.jpg","sClube":"FIGUEIRENSE","sLogo":"http://egol.fcf.com.br/SESP/ClubeLigas/FIGUEIRENSE.png"},{"iGols":2,"sNmJogador":"RILDO DE ANDRADE FELICISSIMO","sApelido":"RILDO","sFoto":"http://egol.fcf.com.br/sesp/Images/39442218859_75_Rildo.png","sClube":"AVAÍ","sLogo":"http://egol.fcf.com.br/SESP/ClubeLigas/avai.png"},{"iGols":2,"sNmJogador":"NATHAN DO REGO FERREIRA","sApelido":"NATHAN FERREIRA","sFoto":"http://egol.fcf.com.br/sesp/Images/41050416813_97_Nat.jpeg","sClube":"MARCÍLIO DIAS","sLogo":"http://egol.fcf.com.br/SESP/ClubeLigas/marciliodias.png"},{"iGols":2,"sNmJogador":"DERLAN DE OLIVEIRA BENTO","sApelido":"DERLAN","sFoto":"http://egol.fcf.com.br/sesp/Images/14534458703_3_derlan.jpg","sClube":"CHAPECOENSE","sLogo":"http://egol.fcf.com.br/SESP/ClubeLigas/Chapecoense.png"},{"iGols":2,"sNmJogador":"MARCO ANTONIO MILITAO JUNIOR","sApelido":"MARCO ANTONIO","sFoto":"http://egol.fcf.com.br/sesp/Images/02066907030_37_Marco.jpg","sClube":"BRUSQUE","sLogo":"http://egol.fcf.com.br/SESP/ClubeLigas/Brusque.png"},{"iGols":2,"sNmJogador":"ROBERTO NASCIMENTO DOS SANTOS","sApelido":"ROBERTO","sFoto":"http://egol.fcf.com.br/sesp/Images/06062098913_39_RP.jpeg","sClube":"MARCÍLIO DIAS","sLogo":"http://egol.fcf.com.br/SESP/ClubeLigas/marciliodias.png"},{"iGols":2,"sNmJogador":"FABIO SOUZA DOS SANTOS","sApelido":"FABINHO","sFoto":"http://egol.fcf.com.br/sesp/Images/32028135875_21_Fabio.jpeg","sClube":"JUVENTUS","sLogo":"http://egol.fcf.com.br/SESP/ClubeLigas/JUVENTUS.png"},{"iGols":3,"sNmJogador":"JONATHAN LUIZ MOREIRA ROSA JÚNIOR","sApelido":"JONATHAN","sFoto":"http://egol.fcf.com.br/sesp/Images/03324571090_96_jhonatan99.png","sClube":"AVAÍ","sLogo":"http://egol.fcf.com.br/SESP/ClubeLigas/avai.png"},{"iGols":3,"sNmJogador":"LUIZ CARLOS MARQUES LIMA","sApelido":"THIAGO ALAGOANO","sFoto":"http://egol.fcf.com.br/sesp/Images/09045865459_54_Thiago.jpg","sClube":"BRUSQUE","sLogo":"http://egol.fcf.com.br/SESP/ClubeLigas/Brusque.png"},{"iGols":3,"sNmJogador":"MARLLON DOS SANTOS PEREIRA","sApelido":"MARLLON","sFoto":"http://egol.fcf.com.br/sesp/Images/02497725314_9_Marllon.jpeg","sClube":"JUVENTUS","sLogo":"http://egol.fcf.com.br/SESP/ClubeLigas/JUVENTUS.png"},{"iGols":3,"sNmJogador":"LEONARDO DE OLIVEIRA CLEMENTE MARTINS","sApelido":"LÉO ITAPERUNA","sFoto":"http://egol.fcf.com.br/sesp/Images/12508317764_64_LEONARD.jpg","sClube":"CONCÓRDIA","sLogo":"http://egol.fcf.com.br/SESP/ClubeLigas/CONCORDIA.png"},{"iGols":3,"sNmJogador":"MOISES VIEIRA DA VEIGA","sApelido":"MOISES","sFoto":"http://egol.fcf.com.br/sesp/Images/11507889925_27_moises.jpg","sClube":"CONCÓRDIA","sLogo":"http://egol.fcf.com.br/SESP/ClubeLigas/CONCORDIA.png"},{"iGols":4,"sNmJogador":"CARLOS CESAR NEVES","sApelido":"CARLOS","sFoto":"http://egol.fcf.com.br/sesp/Images/05700592916_62_Carlos.jpg","sClube":"CRICIÚMA","sLogo":"http://egol.fcf.com.br/SESP/ClubeLigas/CRICIUMA.png"},{"iGols":4,"sNmJogador":"LUCAS HENRIQUE DOS SANTOS","sApelido":"LUQUINHAS","sFoto":"http://egol.fcf.com.br/sesp/Images/09351107477_83_foto3x4.jpg","sClube":"JOINVILLE","sLogo":"http://egol.fcf.com.br/SESP/ClubeLigas/Joinville.png"},{"iGols":6,"sNmJogador":"EDUARDO NASCIMENTO DA SILVA JUNIOR","sApelido":"EDUARDO","sFoto":"http://egol.fcf.com.br/sesp/Images/14364025739_95_Edu2.jpg","sClube":"BRUSQUE","sLogo":"http://egol.fcf.com.br/SESP/ClubeLigas/Brusque.png"}]